fnet_sitemap_to_pdf/__init__.py
fnet_sitemap_to_pdf/cli/__init__.py
fnet_sitemap_to_pdf/cli/index.py
fnet_sitemap_to_pdf/lib/__init__.py
fnet_sitemap_to_pdf/lib/index.py
fnet_sitemap_to_pdf-0.1.10.dist-info/METADATA
fnet_sitemap_to_pdf-0.1.10.dist-info/WHEEL
fnet_sitemap_to_pdf-0.1.10.dist-info/entry_points.txt
fnet_sitemap_to_pdf-0.1.10.dist-info/top_level.txt
fnet_sitemap_to_pdf-0.1.10.dist-info/RECORD
